instascrape/__init__.py
instascrape/client.py
instascrape/compat.py
instascrape/compatpatch.py
instascrape/constants.py
instascrape/errors.py
instascrape/http.py
instascrape/utils.py
instascrape/endpoints/__init__.py
instascrape/endpoints/accounts.py
instascrape/endpoints/collections.py
instascrape/endpoints/common.py
instascrape/endpoints/discover.py
instascrape/endpoints/feed.py
instascrape/endpoints/friendships.py
instascrape/endpoints/highlights.py
instascrape/endpoints/igtv.py
instascrape/endpoints/live.py
instascrape/endpoints/locations.py
instascrape/endpoints/media.py
instascrape/endpoints/misc.py
instascrape/endpoints/tags.py
instascrape/endpoints/upload.py
instascrape/endpoints/users.py
instascrape/endpoints/usertags.py
instascrape/web/__init__.py
instascrape/web/client.py
instascrape/web/common.py
instascrape/web/compat.py
instascrape/web/compatpatch.py
instascrape/web/errors.py
instascrape/web/http.py
instagscrape-1.6.0.dist-info/LICENSE
instagscrape-1.6.0.dist-info/METADATA
instagscrape-1.6.0.dist-info/WHEEL
instagscrape-1.6.0.dist-info/top_level.txt
instagscrape-1.6.0.dist-info/RECORD
