Metadata-Version: 2.1
Name: instagscrape
Version: 1.6.0
Summary: A client interface for the private Instagram API.
Home-page: https://github.com/5hirish/insta_scrapper
Author: Shirish Kadam
Author-email: shirishkadam35@gmail.com
License: mit
Keywords: Instagram scrapper
Platform: UNKNOWN
Classifier: Development Status :: 5 - Production/Stable
Classifier: Intended Audience :: Education
Classifier: Intended Audience :: Developers
Classifier: Intended Audience :: Science/Research
Classifier: Operating System :: OS Independent
Classifier: License :: OSI Approved :: MIT License
Classifier: Programming Language :: Python
Classifier: Programming Language :: Python :: 3
Classifier: Programming Language :: Python :: 3.5
Classifier: Programming Language :: Python :: 3.6
Classifier: Topic :: Software Development :: Libraries :: Python Modules
Classifier: Topic :: Scientific/Engineering
Classifier: Topic :: Scientific/Engineering :: Information Analysis
Requires-Python: >=3.5.*
